{
  "slides": [
    {
      "id": 1,
      "image": "/images/hero/hero1.jpg",
      "title": "Liberation War Heroes",
      "description": "Young freedom fighters ready for battle, 1971"
    },
    {
      "id": 2,
      "image": "/images/hero/hero2.webp",
      "title": "The Fight for Freedom",
      "description": "Mass uprising in Dhaka, March 1971"
    },
    {
      "id": 3,
      "image": "/images/hero/hero3.webp",
      "title": "Victory Day",
      "description": "Celebration of independence, December 16, 1971"
    }
  ]
}
